setup.py
getfontname/__init__.py
getfontname/fontfile.py
getfontname/fontname.py
getfontname.egg-info/PKG-INFO
getfontname.egg-info/SOURCES.txt
getfontname.egg-info/dependency_links.txt
getfontname.egg-info/top_level.txt